wrftamer/Statistics.py
wrftamer/__init__.py
wrftamer/_version.py
wrftamer/initialize_wrf_namelist.py
wrftamer/link_grib.py
wrftamer/main.py
wrftamer/process_tslist_files.py
wrftamer/utility.py
wrftamer/wrfplotter_classes.py
wrftamer/wrftamer_functions.py
wrftamer/wrftamer_paths.py
wrftamer/gui/__init__.py
wrftamer/gui/about_tab.py
wrftamer/gui/exp_tab.py
wrftamer/gui/gui.py
wrftamer/gui/gui_base.py
wrftamer/gui/proj_tab.py
wrftamer/gui/wrfplotter_tab.py
wrftamer/gui/wrfplotter_utility.py
wrftamer/plotting/__init__.py
wrftamer/plotting/hv_plots.py
wrftamer/plotting/load_and_prepare.py
wrftamer/plotting/mpl_plots.py
wrftamer/resources/Levels_per_variable.yaml
wrftamer/resources/cf_table_timeseries_fields.yaml
wrftamer/resources/cf_table_wrfdata.yaml
wrftamer/resources/configure_template.yaml
wrftamer/resources/namelist.template
wrftamer/resources/points_of_interest.csv
wrftamer-1.1.23.data/scripts/run_ppp
wrftamer-1.1.23.data/scripts/wt
wrftamer-1.1.23.data/scripts/wt_gui
wrftamer-1.1.23.dist-info/AUTHORS
wrftamer-1.1.23.dist-info/LICENCE
wrftamer-1.1.23.dist-info/LICENCES.third_party
wrftamer-1.1.23.dist-info/METADATA
wrftamer-1.1.23.dist-info/WHEEL
wrftamer-1.1.23.dist-info/top_level.txt
wrftamer-1.1.23.dist-info/RECORD
