Metadata-Version: 2.1
Name: wrftamer
Version: 1.1.23
Summary: A python package to help you mangaging WRF projects and experiments
Home-page: https://wrftamer.readthedocs.io/en/latest/
Maintainer: Daniel Leukauf
Maintainer-email: daniel.leukauf@zsw-bw.de
License: MIT
Classifier: Programming Language :: Python
Requires-Python: >=3.9.0
License-File: LICENCE
License-File: LICENCES.third_party
License-File: AUTHORS
Requires-Dist: numpy
Requires-Dist: setuptools (>=30.3.0)
Requires-Dist: pandas (>=1.3.5)
Requires-Dist: matplotlib
Requires-Dist: panel
Requires-Dist: pyyaml
Requires-Dist: netcdf4
Requires-Dist: xarray
Requires-Dist: python-crontab
Requires-Dist: click
Requires-Dist: holoviews
Requires-Dist: hvplot
Requires-Dist: windrose (>=1.6.8)
Requires-Dist: wrf-python (>=1.3.1)
Provides-Extra: all
Requires-Dist: mkdocs ; extra == 'all'
Requires-Dist: pytest ; extra == 'all'
Requires-Dist: coverage ; extra == 'all'
Provides-Extra: doc
Requires-Dist: mkdocs ; extra == 'doc'
Provides-Extra: test
Requires-Dist: pytest ; extra == 'test'
Requires-Dist: coverage ; extra == 'test'
